xconfluencebuilder/__init__.py
victorykit_xconfluencebuilder-1.1.2.dist-info/LICENSE
victorykit_xconfluencebuilder-1.1.2.dist-info/METADATA
victorykit_xconfluencebuilder-1.1.2.dist-info/WHEEL
victorykit_xconfluencebuilder-1.1.2.dist-info/top_level.txt
victorykit_xconfluencebuilder-1.1.2.dist-info/zip-safe
victorykit_xconfluencebuilder-1.1.2.dist-info/RECORD
