Metadata-Version: 2.1
Name: victorykit-xconfluencebuilder
Version: 1.1.2
Summary: sphinxcontrib.confluencebuilder wrapper for delayed publishing
Author: Theodor Rodweil
Author-email: theodor.rodweil@victory-k.it
License: DL-DE-BY-2.0
Project-URL: Changelog, https://bitbucket.org/victorykit/xconfluencebuilder/src/master/CHANGELOG.md
Project-URL: Repository, https://bitbucket.org/victorykit/xconfluencebuilder/
Requires-Python: >=3.7
License-File: LICENSE
Requires-Dist: sphinxcontrib-confluencebuilder <3,>=2.2.0
